bilby_cython/.version
bilby_cython/__init__.py
bilby_cython/_version.py
bilby_cython/conftest.py
bilby_cython/geometry.c
bilby_cython/geometry.cp310-win_amd64.pyd
bilby_cython/geometry.pyx
bilby_cython/time.c
bilby_cython/time.cp310-win_amd64.pyd
bilby_cython/time.pyx
bilby_cython/test/__init__.py
bilby_cython/test/old_code.py
bilby_cython/test/test_geometry.py
bilby_cython/test/test_time.py
bilby_cython/test/timing.py
docs/Makefile
docs/conf.py
docs/geometry.rst
docs/index.rst
docs/time.rst
bilby.cython-0.5.3.dist-info/LICENSE
bilby.cython-0.5.3.dist-info/METADATA
bilby.cython-0.5.3.dist-info/WHEEL
bilby.cython-0.5.3.dist-info/top_level.txt
bilby.cython-0.5.3.dist-info/RECORD
