Metadata-Version: 2.1
Name: bilby.cython
Version: 0.5.3
Summary: Optimized functionality for Bilby
Author-email: Colm Talbot <colm.talbot@ligo.org>
License: MIT
Project-URL: Homepage, https://git.ligo.org/colm.talbot/bilby-cython
Classifier: Programming Language :: Python :: 3.9
Classifier: Programming Language :: Python :: 3.10
Classifier: Programming Language :: Python :: 3.11
Classifier: Programming Language :: Python :: 3.12
Classifier: License :: OSI Approved :: MIT License
Classifier: Operating System :: OS Independent
Requires-Python: >=3.9
License-File: LICENSE
Requires-Dist: numpy
